macromrit/__init__.py
macromrit-1.1.11.dist-info/LICENSE.txt
macromrit-1.1.11.dist-info/METADATA
macromrit-1.1.11.dist-info/WHEEL
macromrit-1.1.11.dist-info/top_level.txt
macromrit-1.1.11.dist-info/RECORD
