Metadata-Version: 2.1
Name: macromrit
Version: 1.1.11
Summary: A tiny but compact file writting library... if file writting create's dings, then oppose it with wings :)
Home-page: https://github.com/macromrit/python_package_amrit
Author: C.Amrit Subramanian
Author-email: amritsubramanian.c@gmail.com
License: UNKNOWN
Platform: UNKNOWN
Classifier: Programming Language :: Python :: 3
Classifier: License :: OSI Approved :: MIT License
Classifier: Operating System :: OS Independent
Requires-Python: >=3.6
